{
    "gesture_class": "thumbs_down",
    "landmarks": {
        "WRIST": {
            "x": 0.8472050428390503,
            "y": 0.27298370003700256
        },
        "THUMB_CMC": {
            "x": 0.8782374262809753,
            "y": 0.2984561622142792
        },
        "THUMB_MCP": {
            "x": 0.922705352306366,
            "y": 0.319444864988327
        },
        "THUMB_IP": {
            "x": 0.9542537331581116,
            "y": 0.33593955636024475
        },
        "THUMB_TIP": {
            "x": 0.9752711653709412,
            "y": 0.354150652885437
        },
        "INDEX_FINGER_MCP": {
            "x": 0.9360623359680176,
            "y": 0.30401721596717834
        },
        "INDEX_FINGER_PIP": {
            "x": 0.9656213521957397,
            "y": 0.2881283462047577
        },
        "INDEX_FINGER_DIP": {
            "x": 0.9551571011543274,
            "y": 0.2859027683734894
        },
        "INDEX_FINGER_TIP": {
            "x": 0.940421462059021,
            "y": 0.2906402051448822
        },
        "MIDDLE_FINGER_MCP": {
            "x": 0.9300612807273865,
            "y": 0.2806468904018402
        },
        "MIDDLE_FINGER_PIP": {
            "x": 0.9639610648155212,
            "y": 0.26274657249450684
        },
        "MIDDLE_FINGER_DIP": {
            "x": 0.9514071345329285,
            "y": 0.26304540038108826
        },
        "MIDDLE_FINGER_TIP": {
            "x": 0.9341309070587158,
            "y": 0.26877614855766296
        },
        "RING_FINGER_MCP": {
            "x": 0.9209035038948059,
            "y": 0.2564559578895569
        },
        "RING_FINGER_PIP": {
            "x": 0.9531328082084656,
            "y": 0.23837921023368835
        },
        "RING_FINGER_DIP": {
            "x": 0.94048011302948,
            "y": 0.24051517248153687
        },
        "RING_FINGER_TIP": {
            "x": 0.9246066212654114,
            "y": 0.24802714586257935
        },
        "PINKY_MCP": {
            "x": 0.9103326201438904,
            "y": 0.2326507866382599
        },
        "PINKY_PIP": {
            "x": 0.9372979998588562,
            "y": 0.2191862165927887
        },
        "PINKY_DIP": {
            "x": 0.926362931728363,
            "y": 0.22201302647590637
        },
        "PINKY_TIP": {
            "x": 0.9123364090919495,
            "y": 0.22835108637809753
        }
    }
}