{
    "gesture_class": "B-sign",
    "landmarks": {
        "WRIST": {
            "x": 0.7630335688591003,
            "y": 0.36277222633361816,
            "z": 4.0098066733662563e-07
        },
        "THUMB_CMC": {
            "x": 0.7256991267204285,
            "y": 0.35630807280540466,
            "z": -0.017702806740999222
        },
        "THUMB_MCP": {
            "x": 0.7040516138076782,
            "y": 0.33631524443626404,
            "z": -0.030104903504252434
        },
        "THUMB_IP": {
            "x": 0.7161948084831238,
            "y": 0.31747159361839294,
            "z": -0.041726935654878616
        },
        "THUMB_TIP": {
            "x": 0.7400509119033813,
            "y": 0.30892643332481384,
            "z": -0.05324035510420799
        },
        "INDEX_FINGER_MCP": {
            "x": 0.6944868564605713,
            "y": 0.29964181780815125,
            "z": -0.023703554645180702
        },
        "INDEX_FINGER_PIP": {
            "x": 0.6845146417617798,
            "y": 0.26675525307655334,
            "z": -0.04253358393907547
        },
        "INDEX_FINGER_DIP": {
            "x": 0.6811791658401489,
            "y": 0.24496814608573914,
            "z": -0.057390451431274414
        },
        "INDEX_FINGER_TIP": {
            "x": 0.6802458167076111,
            "y": 0.22680562734603882,
            "z": -0.06792473047971725
        },
        "MIDDLE_FINGER_MCP": {
            "x": 0.715877890586853,
            "y": 0.29697397351264954,
            "z": -0.02838011085987091
        },
        "MIDDLE_FINGER_PIP": {
            "x": 0.7064100503921509,
            "y": 0.2615868151187897,
            "z": -0.04393596202135086
        },
        "MIDDLE_FINGER_DIP": {
            "x": 0.703518807888031,
            "y": 0.23748989403247833,
            "z": -0.05697896331548691
        },
        "MIDDLE_FINGER_TIP": {
            "x": 0.7039023637771606,
            "y": 0.21803417801856995,
            "z": -0.0660317912697792
        },
        "RING_FINGER_MCP": {
            "x": 0.7395857572555542,
            "y": 0.29969117045402527,
            "z": -0.03484777733683586
        },
        "RING_FINGER_PIP": {
            "x": 0.7318111062049866,
            "y": 0.2683797776699066,
            "z": -0.04734422639012337
        },
        "RING_FINGER_DIP": {
            "x": 0.7283771634101868,
            "y": 0.24749620258808136,
            "z": -0.05669688433408737
        },
        "RING_FINGER_TIP": {
            "x": 0.7276079058647156,
            "y": 0.23096546530723572,
            "z": -0.06323320418596268
        },
        "PINKY_MCP": {
            "x": 0.7652866244316101,
            "y": 0.3072551488876343,
            "z": -0.04347362741827965
        },
        "PINKY_PIP": {
            "x": 0.7594801187515259,
            "y": 0.28421977162361145,
            "z": -0.05471615865826607
        },
        "PINKY_DIP": {
            "x": 0.7540224194526672,
            "y": 0.26847440004348755,
            "z": -0.05943015590310097
        },
        "PINKY_TIP": {
            "x": 0.7500544786453247,
            "y": 0.25573500990867615,
            "z": -0.06218066066503525
        }
    }
}