{
    "gesture_class": "C-pos_1",
    "landmarks": {
        "WRIST": {
            "x": 0.7084243893623352,
            "y": 0.4893995523452759
        },
        "THUMB_CMC": {
            "x": 0.6728336215019226,
            "y": 0.48701488971710205
        },
        "THUMB_MCP": {
            "x": 0.6371381282806396,
            "y": 0.4648899435997009
        },
        "THUMB_IP": {
            "x": 0.608752965927124,
            "y": 0.4545058310031891
        },
        "THUMB_TIP": {
            "x": 0.5812535285949707,
            "y": 0.4472448229789734
        },
        "INDEX_FINGER_MCP": {
            "x": 0.6714827418327332,
            "y": 0.4080269932746887
        },
        "INDEX_FINGER_PIP": {
            "x": 0.6624007821083069,
            "y": 0.3751123547554016
        },
        "INDEX_FINGER_DIP": {
            "x": 0.6375938057899475,
            "y": 0.3684070110321045
        },
        "INDEX_FINGER_TIP": {
            "x": 0.6141595244407654,
            "y": 0.37346386909484863
        },
        "MIDDLE_FINGER_MCP": {
            "x": 0.68593829870224,
            "y": 0.40877565741539
        },
        "MIDDLE_FINGER_PIP": {
            "x": 0.6755278706550598,
            "y": 0.37259727716445923
        },
        "MIDDLE_FINGER_DIP": {
            "x": 0.6440497040748596,
            "y": 0.3707524240016937
        },
        "MIDDLE_FINGER_TIP": {
            "x": 0.6185943484306335,
            "y": 0.3792846202850342
        },
        "RING_FINGER_MCP": {
            "x": 0.6996636390686035,
            "y": 0.4159698486328125
        },
        "RING_FINGER_PIP": {
            "x": 0.6864897012710571,
            "y": 0.3810517191886902
        },
        "RING_FINGER_DIP": {
            "x": 0.6545627117156982,
            "y": 0.37950780987739563
        },
        "RING_FINGER_TIP": {
            "x": 0.6302312016487122,
            "y": 0.38743630051612854
        },
        "PINKY_MCP": {
            "x": 0.7096418738365173,
            "y": 0.429188072681427
        },
        "PINKY_PIP": {
            "x": 0.6917580366134644,
            "y": 0.4015750288963318
        },
        "PINKY_DIP": {
            "x": 0.6673402190208435,
            "y": 0.3946392238140106
        },
        "PINKY_TIP": {
            "x": 0.6477009057998657,
            "y": 0.3958255350589752
        }
    }
}