{
    "gesture_class": "Okay",
    "landmarks": {
        "WRIST": {
            "x": 0.5030904412269592,
            "y": 0.3398420810699463,
            "z": 7.545644109541172e-08
        },
        "THUMB_CMC": {
            "x": 0.473184734582901,
            "y": 0.34417295455932617,
            "z": -0.010381988249719143
        },
        "THUMB_MCP": {
            "x": 0.4435451328754425,
            "y": 0.33625853061676025,
            "z": -0.020078938454389572
        },
        "THUMB_IP": {
            "x": 0.4220517873764038,
            "y": 0.33131885528564453,
            "z": -0.03008234314620495
        },
        "THUMB_TIP": {
            "x": 0.4083516001701355,
            "y": 0.32280129194259644,
            "z": -0.039367325603961945
        },
        "INDEX_FINGER_MCP": {
            "x": 0.43945878744125366,
            "y": 0.2855449318885803,
            "z": -0.011391778476536274
        },
        "INDEX_FINGER_PIP": {
            "x": 0.4110086262226105,
            "y": 0.2726370394229889,
            "z": -0.03239723667502403
        },
        "INDEX_FINGER_DIP": {
            "x": 0.40310728549957275,
            "y": 0.2892927825450897,
            "z": -0.04990103468298912
        },
        "INDEX_FINGER_TIP": {
            "x": 0.4049859046936035,
            "y": 0.30627572536468506,
            "z": -0.05831185355782509
        },
        "MIDDLE_FINGER_MCP": {
            "x": 0.450723260641098,
            "y": 0.2757090926170349,
            "z": -0.015005718916654587
        },
        "MIDDLE_FINGER_PIP": {
            "x": 0.4282045066356659,
            "y": 0.24399805068969727,
            "z": -0.026706481352448463
        },
        "MIDDLE_FINGER_DIP": {
            "x": 0.41110655665397644,
            "y": 0.22606678307056427,
            "z": -0.03557989001274109
        },
        "MIDDLE_FINGER_TIP": {
            "x": 0.3979038596153259,
            "y": 0.2101323902606964,
            "z": -0.04072396457195282
        },
        "RING_FINGER_MCP": {
            "x": 0.4668155610561371,
            "y": 0.2737247943878174,
            "z": -0.021370843052864075
        },
        "RING_FINGER_PIP": {
            "x": 0.4515126943588257,
            "y": 0.2398899495601654,
            "z": -0.032311659306287766
        },
        "RING_FINGER_DIP": {
            "x": 0.4381198287010193,
            "y": 0.21954350173473358,
            "z": -0.039441946893930435
        },
        "RING_FINGER_TIP": {
            "x": 0.427213191986084,
            "y": 0.2025502324104309,
            "z": -0.042961858212947845
        },
        "PINKY_MCP": {
            "x": 0.486176073551178,
            "y": 0.28008371591567993,
            "z": -0.028750967234373093
        },
        "PINKY_PIP": {
            "x": 0.48478493094444275,
            "y": 0.25438809394836426,
            "z": -0.03669535368680954
        },
        "PINKY_DIP": {
            "x": 0.48114222288131714,
            "y": 0.2369500696659088,
            "z": -0.037452418357133865
        },
        "PINKY_TIP": {
            "x": 0.4787794351577759,
            "y": 0.22178712487220764,
            "z": -0.0364631749689579
        }
    }
}