{
    "gesture_class": "B-sign",
    "landmarks": {
        "WRIST": {
            "x": 0.6630991101264954,
            "y": 0.4107681214809418
        },
        "THUMB_CMC": {
            "x": 0.6329723000526428,
            "y": 0.39949801564216614
        },
        "THUMB_MCP": {
            "x": 0.6187286376953125,
            "y": 0.3756457567214966
        },
        "THUMB_IP": {
            "x": 0.6339866518974304,
            "y": 0.35539868474006653
        },
        "THUMB_TIP": {
            "x": 0.6574813723564148,
            "y": 0.3460204303264618
        },
        "INDEX_FINGER_MCP": {
            "x": 0.6128680109977722,
            "y": 0.33214372396469116
        },
        "INDEX_FINGER_PIP": {
            "x": 0.6073912978172302,
            "y": 0.29273247718811035
        },
        "INDEX_FINGER_DIP": {
            "x": 0.6059566736221313,
            "y": 0.2682919502258301
        },
        "INDEX_FINGER_TIP": {
            "x": 0.6056068539619446,
            "y": 0.24708664417266846
        },
        "MIDDLE_FINGER_MCP": {
            "x": 0.6317171454429626,
            "y": 0.32974570989608765
        },
        "MIDDLE_FINGER_PIP": {
            "x": 0.6258169412612915,
            "y": 0.2883630692958832
        },
        "MIDDLE_FINGER_DIP": {
            "x": 0.6240854263305664,
            "y": 0.2607686519622803
        },
        "MIDDLE_FINGER_TIP": {
            "x": 0.6234090924263,
            "y": 0.23703821003437042
        },
        "RING_FINGER_MCP": {
            "x": 0.6520370841026306,
            "y": 0.3335391879081726
        },
        "RING_FINGER_PIP": {
            "x": 0.6471645832061768,
            "y": 0.29605016112327576
        },
        "RING_FINGER_DIP": {
            "x": 0.6448700428009033,
            "y": 0.27192243933677673
        },
        "RING_FINGER_TIP": {
            "x": 0.6430138945579529,
            "y": 0.25128865242004395
        },
        "PINKY_MCP": {
            "x": 0.6742693781852722,
            "y": 0.34291213750839233
        },
        "PINKY_PIP": {
            "x": 0.6701444387435913,
            "y": 0.31523194909095764
        },
        "PINKY_DIP": {
            "x": 0.6660706400871277,
            "y": 0.2959117293357849
        },
        "PINKY_TIP": {
            "x": 0.6627236604690552,
            "y": 0.2791067659854889
        }
    }
}