{
    "gesture_class": "peace_sign",
    "landmarks": {
        "WRIST": {
            "x": 0.7337523102760315,
            "y": 0.3727971315383911
        },
        "THUMB_CMC": {
            "x": 0.6941704750061035,
            "y": 0.3566974997520447
        },
        "THUMB_MCP": {
            "x": 0.6659650206565857,
            "y": 0.33090314269065857
        },
        "THUMB_IP": {
            "x": 0.668154776096344,
            "y": 0.3064853847026825
        },
        "THUMB_TIP": {
            "x": 0.6844612956047058,
            "y": 0.2836815118789673
        },
        "INDEX_FINGER_MCP": {
            "x": 0.6745443940162659,
            "y": 0.23999957740306854
        },
        "INDEX_FINGER_PIP": {
            "x": 0.658958911895752,
            "y": 0.18070369958877563
        },
        "INDEX_FINGER_DIP": {
            "x": 0.6530482172966003,
            "y": 0.1403200626373291
        },
        "INDEX_FINGER_TIP": {
            "x": 0.64983069896698,
            "y": 0.10724009573459625
        },
        "MIDDLE_FINGER_MCP": {
            "x": 0.7092803716659546,
            "y": 0.24093961715698242
        },
        "MIDDLE_FINGER_PIP": {
            "x": 0.7151384949684143,
            "y": 0.17187488079071045
        },
        "MIDDLE_FINGER_DIP": {
            "x": 0.7208184599876404,
            "y": 0.12721402943134308
        },
        "MIDDLE_FINGER_TIP": {
            "x": 0.7282604575157166,
            "y": 0.09177432954311371
        },
        "RING_FINGER_MCP": {
            "x": 0.7412118911743164,
            "y": 0.2583461403846741
        },
        "RING_FINGER_PIP": {
            "x": 0.7304751873016357,
            "y": 0.22955581545829773
        },
        "RING_FINGER_DIP": {
            "x": 0.7142011523246765,
            "y": 0.26082682609558105
        },
        "RING_FINGER_TIP": {
            "x": 0.7105153203010559,
            "y": 0.2864614725112915
        },
        "PINKY_MCP": {
            "x": 0.7662754058837891,
            "y": 0.28647804260253906
        },
        "PINKY_PIP": {
            "x": 0.748103141784668,
            "y": 0.26972872018814087
        },
        "PINKY_DIP": {
            "x": 0.7318947911262512,
            "y": 0.29243457317352295
        },
        "PINKY_TIP": {
            "x": 0.7287567853927612,
            "y": 0.31203407049179077
        }
    }
}