{
    "gesture_class": "peace_sign",
    "landmarks": {
        "WRIST": {
            "x": 0.6731932163238525,
            "y": 0.4324515759944916,
            "z": 9.261335662813508e-07
        },
        "THUMB_CMC": {
            "x": 0.6313895583152771,
            "y": 0.417464017868042,
            "z": -0.025374367833137512
        },
        "THUMB_MCP": {
            "x": 0.603585958480835,
            "y": 0.3828544020652771,
            "z": -0.046270765364170074
        },
        "THUMB_IP": {
            "x": 0.6083917617797852,
            "y": 0.3518342971801758,
            "z": -0.06870774179697037
        },
        "THUMB_TIP": {
            "x": 0.6229549646377563,
            "y": 0.3255172669887543,
            "z": -0.09005600959062576
        },
        "INDEX_FINGER_MCP": {
            "x": 0.6215915679931641,
            "y": 0.2858521640300751,
            "z": -0.037031907588243484
        },
        "INDEX_FINGER_PIP": {
            "x": 0.6109232306480408,
            "y": 0.21906131505966187,
            "z": -0.06883509457111359
        },
        "INDEX_FINGER_DIP": {
            "x": 0.6088467836380005,
            "y": 0.1716567426919937,
            "z": -0.0883578285574913
        },
        "INDEX_FINGER_TIP": {
            "x": 0.6102955937385559,
            "y": 0.1332334280014038,
            "z": -0.09948412328958511
        },
        "MIDDLE_FINGER_MCP": {
            "x": 0.6577896475791931,
            "y": 0.28968626260757446,
            "z": -0.048092879354953766
        },
        "MIDDLE_FINGER_PIP": {
            "x": 0.6707960367202759,
            "y": 0.21224242448806763,
            "z": -0.08080194145441055
        },
        "MIDDLE_FINGER_DIP": {
            "x": 0.680192768573761,
            "y": 0.1629689633846283,
            "z": -0.09927917271852493
        },
        "MIDDLE_FINGER_TIP": {
            "x": 0.691705048084259,
            "y": 0.12353149056434631,
            "z": -0.10673253983259201
        },
        "RING_FINGER_MCP": {
            "x": 0.6912477612495422,
            "y": 0.3112230598926544,
            "z": -0.06121287867426872
        },
        "RING_FINGER_PIP": {
            "x": 0.6812238097190857,
            "y": 0.2723642885684967,
            "z": -0.10410407930612564
        },
        "RING_FINGER_DIP": {
            "x": 0.6584956049919128,
            "y": 0.30980223417282104,
            "z": -0.10593412816524506
        },
        "RING_FINGER_TIP": {
            "x": 0.6513055562973022,
            "y": 0.3400695323944092,
            "z": -0.09405780583620071
        },
        "PINKY_MCP": {
            "x": 0.7161160111427307,
            "y": 0.34517425298690796,
            "z": -0.07603662461042404
        },
        "PINKY_PIP": {
            "x": 0.6961616277694702,
            "y": 0.3209340572357178,
            "z": -0.10844765603542328
        },
        "PINKY_DIP": {
            "x": 0.6754659414291382,
            "y": 0.3457827568054199,
            "z": -0.1020408570766449
        },
        "PINKY_TIP": {
            "x": 0.6700417995452881,
            "y": 0.3681032657623291,
            "z": -0.08800642192363739
        }
    }
}