{
    "gesture_class": "Okay",
    "landmarks": {
        "WRIST": {
            "x": 0.6743029356002808,
            "y": 0.36912596225738525
        },
        "THUMB_CMC": {
            "x": 0.6370494365692139,
            "y": 0.3267134130001068
        },
        "THUMB_MCP": {
            "x": 0.618041455745697,
            "y": 0.2831628620624542
        },
        "THUMB_IP": {
            "x": 0.595960259437561,
            "y": 0.2548736035823822
        },
        "THUMB_TIP": {
            "x": 0.572223424911499,
            "y": 0.23170334100723267
        },
        "INDEX_FINGER_MCP": {
            "x": 0.6822136044502258,
            "y": 0.24712108075618744
        },
        "INDEX_FINGER_PIP": {
            "x": 0.6576761603355408,
            "y": 0.19852882623672485
        },
        "INDEX_FINGER_DIP": {
            "x": 0.6157553195953369,
            "y": 0.2017199844121933
        },
        "INDEX_FINGER_TIP": {
            "x": 0.5793420672416687,
            "y": 0.21364319324493408
        },
        "MIDDLE_FINGER_MCP": {
            "x": 0.6996520757675171,
            "y": 0.2554508149623871
        },
        "MIDDLE_FINGER_PIP": {
            "x": 0.7109180092811584,
            "y": 0.19487646222114563
        },
        "MIDDLE_FINGER_DIP": {
            "x": 0.7004417777061462,
            "y": 0.15648320317268372
        },
        "MIDDLE_FINGER_TIP": {
            "x": 0.6896082758903503,
            "y": 0.12475897371768951
        },
        "RING_FINGER_MCP": {
            "x": 0.7088498473167419,
            "y": 0.2763713300228119
        },
        "RING_FINGER_PIP": {
            "x": 0.7371616363525391,
            "y": 0.224419504404068
        },
        "RING_FINGER_DIP": {
            "x": 0.740024745464325,
            "y": 0.1894192099571228
        },
        "RING_FINGER_TIP": {
            "x": 0.7401582598686218,
            "y": 0.1582702398300171
        },
        "PINKY_MCP": {
            "x": 0.7087161540985107,
            "y": 0.304699569940567
        },
        "PINKY_PIP": {
            "x": 0.7385513782501221,
            "y": 0.2803546190261841
        },
        "PINKY_DIP": {
            "x": 0.7522580027580261,
            "y": 0.25962454080581665
        },
        "PINKY_TIP": {
            "x": 0.7629632353782654,
            "y": 0.23870480060577393
        }
    }
}