{
    "gesture_class": "thumbs_up",
    "landmarks": {
        "WRIST": {
            "x": 0.6900964975357056,
            "y": 0.5551842451095581
        },
        "THUMB_CMC": {
            "x": 0.6487253308296204,
            "y": 0.4919825494289398
        },
        "THUMB_MCP": {
            "x": 0.6416937708854675,
            "y": 0.4180968403816223
        },
        "THUMB_IP": {
            "x": 0.6575049161911011,
            "y": 0.36084625124931335
        },
        "THUMB_TIP": {
            "x": 0.6747651696205139,
            "y": 0.31506386399269104
        },
        "INDEX_FINGER_MCP": {
            "x": 0.7058378458023071,
            "y": 0.4289635121822357
        },
        "INDEX_FINGER_PIP": {
            "x": 0.6344597339630127,
            "y": 0.4666977822780609
        },
        "INDEX_FINGER_DIP": {
            "x": 0.6326388120651245,
            "y": 0.4795330762863159
        },
        "INDEX_FINGER_TIP": {
            "x": 0.6543210744857788,
            "y": 0.4659414291381836
        },
        "MIDDLE_FINGER_MCP": {
            "x": 0.7342056035995483,
            "y": 0.46739211678504944
        },
        "MIDDLE_FINGER_PIP": {
            "x": 0.6378269791603088,
            "y": 0.5037344098091125
        },
        "MIDDLE_FINGER_DIP": {
            "x": 0.6451662182807922,
            "y": 0.5064409971237183
        },
        "MIDDLE_FINGER_TIP": {
            "x": 0.6690640449523926,
            "y": 0.4928778111934662
        },
        "RING_FINGER_MCP": {
            "x": 0.747776210308075,
            "y": 0.5037283897399902
        },
        "RING_FINGER_PIP": {
            "x": 0.6521713137626648,
            "y": 0.5352403521537781
        },
        "RING_FINGER_DIP": {
            "x": 0.6565768122673035,
            "y": 0.5380779504776001
        },
        "RING_FINGER_TIP": {
            "x": 0.6799405813217163,
            "y": 0.5264006853103638
        },
        "PINKY_MCP": {
            "x": 0.7482495307922363,
            "y": 0.5368268489837646
        },
        "PINKY_PIP": {
            "x": 0.6759238243103027,
            "y": 0.5623018145561218
        },
        "PINKY_DIP": {
            "x": 0.6748759746551514,
            "y": 0.5644937753677368
        },
        "PINKY_TIP": {
            "x": 0.694455623626709,
            "y": 0.5572253465652466
        }
    }
}