{
    "gesture_class": "palm_up",
    "landmarks": {
        "WRIST": {
            "x": 0.8094800710678101,
            "y": 0.5183430910110474,
            "z": 3.562028041415033e-07
        },
        "THUMB_CMC": {
            "x": 0.7654203772544861,
            "y": 0.5060656666755676,
            "z": -0.02791745588183403
        },
        "THUMB_MCP": {
            "x": 0.7397448420524597,
            "y": 0.47996005415916443,
            "z": -0.043730154633522034
        },
        "THUMB_IP": {
            "x": 0.7254276871681213,
            "y": 0.45506036281585693,
            "z": -0.05667954683303833
        },
        "THUMB_TIP": {
            "x": 0.7047713994979858,
            "y": 0.4357450008392334,
            "z": -0.06964879482984543
        },
        "INDEX_FINGER_MCP": {
            "x": 0.7798091769218445,
            "y": 0.44601601362228394,
            "z": -0.032160792499780655
        },
        "INDEX_FINGER_PIP": {
            "x": 0.7827118039131165,
            "y": 0.4090712368488312,
            "z": -0.054545678198337555
        },
        "INDEX_FINGER_DIP": {
            "x": 0.7853314876556396,
            "y": 0.3856711983680725,
            "z": -0.07110966742038727
        },
        "INDEX_FINGER_TIP": {
            "x": 0.7889447212219238,
            "y": 0.36535704135894775,
            "z": -0.08203431963920593
        },
        "MIDDLE_FINGER_MCP": {
            "x": 0.8085576891899109,
            "y": 0.44345176219940186,
            "z": -0.031973958015441895
        },
        "MIDDLE_FINGER_PIP": {
            "x": 0.8118434548377991,
            "y": 0.4033399224281311,
            "z": -0.05109136179089546
        },
        "MIDDLE_FINGER_DIP": {
            "x": 0.8139764666557312,
            "y": 0.3769772946834564,
            "z": -0.06533196568489075
        },
        "MIDDLE_FINGER_TIP": {
            "x": 0.8168512582778931,
            "y": 0.3534420132637024,
            "z": -0.07505185157060623
        },
        "RING_FINGER_MCP": {
            "x": 0.8344228267669678,
            "y": 0.44675272703170776,
            "z": -0.034741632640361786
        },
        "RING_FINGER_PIP": {
            "x": 0.8382856845855713,
            "y": 0.40989169478416443,
            "z": -0.051253221929073334
        },
        "RING_FINGER_DIP": {
            "x": 0.8396214246749878,
            "y": 0.3873647153377533,
            "z": -0.05959579348564148
        },
        "RING_FINGER_TIP": {
            "x": 0.8410711288452148,
            "y": 0.3674872815608978,
            "z": -0.06480655074119568
        },
        "PINKY_MCP": {
            "x": 0.8592100739479065,
            "y": 0.45486459136009216,
            "z": -0.040201298892498016
        },
        "PINKY_PIP": {
            "x": 0.8624160885810852,
            "y": 0.4260609447956085,
            "z": -0.05334242060780525
        },
        "PINKY_DIP": {
            "x": 0.8634276390075684,
            "y": 0.4084089994430542,
            "z": -0.05738026276230812
        },
        "PINKY_TIP": {
            "x": 0.8637014031410217,
            "y": 0.3923206627368927,
            "z": -0.05945774167776108
        }
    }
}