{
    "gesture_class": "thumbs_down",
    "landmarks": {
        "WRIST": {
            "x": 0.7309386730194092,
            "y": 0.524577260017395,
            "z": -3.5308147516843746e-07
        },
        "THUMB_CMC": {
            "x": 0.6862383484840393,
            "y": 0.5502908229827881,
            "z": -0.01397134829312563
        },
        "THUMB_MCP": {
            "x": 0.6432490348815918,
            "y": 0.5618829131126404,
            "z": -0.026645604521036148
        },
        "THUMB_IP": {
            "x": 0.6155205965042114,
            "y": 0.574955940246582,
            "z": -0.039156947284936905
        },
        "THUMB_TIP": {
            "x": 0.5949492454528809,
            "y": 0.589032769203186,
            "z": -0.04847295582294464
        },
        "INDEX_FINGER_MCP": {
            "x": 0.6101837754249573,
            "y": 0.49767303466796875,
            "z": -0.005861290730535984
        },
        "INDEX_FINGER_PIP": {
            "x": 0.5909621119499207,
            "y": 0.5371377468109131,
            "z": -0.025719644501805305
        },
        "INDEX_FINGER_DIP": {
            "x": 0.6234405636787415,
            "y": 0.5431488156318665,
            "z": -0.041757889091968536
        },
        "INDEX_FINGER_TIP": {
            "x": 0.6340767741203308,
            "y": 0.5324627757072449,
            "z": -0.05294899269938469
        },
        "MIDDLE_FINGER_MCP": {
            "x": 0.6183115243911743,
            "y": 0.4823460578918457,
            "z": -0.008353430777788162
        },
        "MIDDLE_FINGER_PIP": {
            "x": 0.6009160280227661,
            "y": 0.5280085802078247,
            "z": -0.026625335216522217
        },
        "MIDDLE_FINGER_DIP": {
            "x": 0.6327371597290039,
            "y": 0.5336869359016418,
            "z": -0.03239617869257927
        },
        "MIDDLE_FINGER_TIP": {
            "x": 0.640856146812439,
            "y": 0.5216435194015503,
            "z": -0.03582895174622536
        },
        "RING_FINGER_MCP": {
            "x": 0.6347789764404297,
            "y": 0.4750158190727234,
            "z": -0.01394984032958746
        },
        "RING_FINGER_PIP": {
            "x": 0.6170840859413147,
            "y": 0.5170674324035645,
            "z": -0.02779223583638668
        },
        "RING_FINGER_DIP": {
            "x": 0.6435617208480835,
            "y": 0.5250789523124695,
            "z": -0.02104519121348858
        },
        "RING_FINGER_TIP": {
            "x": 0.6515940427780151,
            "y": 0.5151547193527222,
            "z": -0.016248071566224098
        },
        "PINKY_MCP": {
            "x": 0.6544219255447388,
            "y": 0.4744429290294647,
            "z": -0.022032180801033974
        },
        "PINKY_PIP": {
            "x": 0.6396040320396423,
            "y": 0.5076984167098999,
            "z": -0.0302016269415617
        },
        "PINKY_DIP": {
            "x": 0.6555780172348022,
            "y": 0.5145556926727295,
            "z": -0.025717122480273247
        },
        "PINKY_TIP": {
            "x": 0.6642062664031982,
            "y": 0.5057595372200012,
            "z": -0.02117144502699375
        }
    }
}