{
    "gesture_class": "B-sign",
    "landmarks": {
        "WRIST": {
            "x": 0.7015655040740967,
            "y": 0.5222905874252319
        },
        "THUMB_CMC": {
            "x": 0.6395278573036194,
            "y": 0.4875178039073944
        },
        "THUMB_MCP": {
            "x": 0.6113287210464478,
            "y": 0.42790788412094116
        },
        "THUMB_IP": {
            "x": 0.6458501815795898,
            "y": 0.3772544264793396
        },
        "THUMB_TIP": {
            "x": 0.6958383917808533,
            "y": 0.36125048995018005
        },
        "INDEX_FINGER_MCP": {
            "x": 0.6132068634033203,
            "y": 0.35020697116851807
        },
        "INDEX_FINGER_PIP": {
            "x": 0.60740065574646,
            "y": 0.2811998426914215
        },
        "INDEX_FINGER_DIP": {
            "x": 0.6115593910217285,
            "y": 0.24023780226707458
        },
        "INDEX_FINGER_TIP": {
            "x": 0.6182089447975159,
            "y": 0.2048782855272293
        },
        "MIDDLE_FINGER_MCP": {
            "x": 0.6541416049003601,
            "y": 0.34258878231048584
        },
        "MIDDLE_FINGER_PIP": {
            "x": 0.6489334106445312,
            "y": 0.2681797742843628
        },
        "MIDDLE_FINGER_DIP": {
            "x": 0.6516322493553162,
            "y": 0.22085243463516235
        },
        "MIDDLE_FINGER_TIP": {
            "x": 0.6538732051849365,
            "y": 0.18071001768112183
        },
        "RING_FINGER_MCP": {
            "x": 0.6956163644790649,
            "y": 0.34910616278648376
        },
        "RING_FINGER_PIP": {
            "x": 0.6912378072738647,
            "y": 0.27842503786087036
        },
        "RING_FINGER_DIP": {
            "x": 0.6908013224601746,
            "y": 0.23501428961753845
        },
        "RING_FINGER_TIP": {
            "x": 0.6896678805351257,
            "y": 0.19844314455986023
        },
        "PINKY_MCP": {
            "x": 0.7390303015708923,
            "y": 0.36660870909690857
        },
        "PINKY_PIP": {
            "x": 0.7367998957633972,
            "y": 0.3122728168964386
        },
        "PINKY_DIP": {
            "x": 0.7330966591835022,
            "y": 0.2754957675933838
        },
        "PINKY_TIP": {
            "x": 0.7288002967834473,
            "y": 0.24426837265491486
        }
    }
}