{
    "gesture_class": "B-stop",
    "landmarks": {
        "WRIST": {
            "x": 0.6774036288261414,
            "y": 0.40447747707366943
        },
        "THUMB_CMC": {
            "x": 0.643052875995636,
            "y": 0.3932665288448334
        },
        "THUMB_MCP": {
            "x": 0.6198110580444336,
            "y": 0.3682015836238861
        },
        "THUMB_IP": {
            "x": 0.6301905512809753,
            "y": 0.3411448895931244
        },
        "THUMB_TIP": {
            "x": 0.6528896689414978,
            "y": 0.3337229788303375
        },
        "INDEX_FINGER_MCP": {
            "x": 0.6130289435386658,
            "y": 0.33010753989219666
        },
        "INDEX_FINGER_PIP": {
            "x": 0.6028788089752197,
            "y": 0.29560214281082153
        },
        "INDEX_FINGER_DIP": {
            "x": 0.5999370217323303,
            "y": 0.27475711703300476
        },
        "INDEX_FINGER_TIP": {
            "x": 0.5978199243545532,
            "y": 0.2565925717353821
        },
        "MIDDLE_FINGER_MCP": {
            "x": 0.6325820684432983,
            "y": 0.3226103186607361
        },
        "MIDDLE_FINGER_PIP": {
            "x": 0.6223766803741455,
            "y": 0.2860117554664612
        },
        "MIDDLE_FINGER_DIP": {
            "x": 0.6194745898246765,
            "y": 0.264224112033844
        },
        "MIDDLE_FINGER_TIP": {
            "x": 0.6177918910980225,
            "y": 0.24572542309761047
        },
        "RING_FINGER_MCP": {
            "x": 0.6532121300697327,
            "y": 0.3221907913684845
        },
        "RING_FINGER_PIP": {
            "x": 0.6449559330940247,
            "y": 0.2907267212867737
        },
        "RING_FINGER_DIP": {
            "x": 0.6413410902023315,
            "y": 0.2710202634334564
        },
        "RING_FINGER_TIP": {
            "x": 0.6387652158737183,
            "y": 0.25526532530784607
        },
        "PINKY_MCP": {
            "x": 0.6754199862480164,
            "y": 0.32749658823013306
        },
        "PINKY_PIP": {
            "x": 0.6697397232055664,
            "y": 0.30529114603996277
        },
        "PINKY_DIP": {
            "x": 0.6663515567779541,
            "y": 0.29042938351631165
        },
        "PINKY_TIP": {
            "x": 0.6650561690330505,
            "y": 0.2788732349872589
        }
    }
}