{
    "gesture_class": "A-sign",
    "landmarks": {
        "WRIST": {
            "x": 0.7934332489967346,
            "y": 0.7702832221984863,
            "z": -7.236237138386059e-07
        },
        "THUMB_CMC": {
            "x": 0.7440994381904602,
            "y": 0.73558109998703,
            "z": -0.005610034801065922
        },
        "THUMB_MCP": {
            "x": 0.7156515121459961,
            "y": 0.6791045069694519,
            "z": -0.006971484981477261
        },
        "THUMB_IP": {
            "x": 0.7081559896469116,
            "y": 0.6349852085113525,
            "z": -0.010508841834962368
        },
        "THUMB_TIP": {
            "x": 0.7041699290275574,
            "y": 0.5973093509674072,
            "z": -0.01189656276255846
        },
        "INDEX_FINGER_MCP": {
            "x": 0.7518672943115234,
            "y": 0.6231963038444519,
            "z": 0.0105716148391366
        },
        "INDEX_FINGER_PIP": {
            "x": 0.7324774861335754,
            "y": 0.6293466091156006,
            "z": -0.010151250287890434
        },
        "INDEX_FINGER_DIP": {
            "x": 0.7353882193565369,
            "y": 0.6690977811813354,
            "z": -0.027581296861171722
        },
        "INDEX_FINGER_TIP": {
            "x": 0.7400749921798706,
            "y": 0.7004173398017883,
            "z": -0.03541848435997963
        },
        "MIDDLE_FINGER_MCP": {
            "x": 0.7850084900856018,
            "y": 0.6238784193992615,
            "z": 0.005871336441487074
        },
        "MIDDLE_FINGER_PIP": {
            "x": 0.7605409026145935,
            "y": 0.6426037549972534,
            "z": -0.011592068709433079
        },
        "MIDDLE_FINGER_DIP": {
            "x": 0.7623378038406372,
            "y": 0.6840972304344177,
            "z": -0.020598076283931732
        },
        "MIDDLE_FINGER_TIP": {
            "x": 0.7648235559463501,
            "y": 0.7174174189567566,
            "z": -0.021875843405723572
        },
        "RING_FINGER_MCP": {
            "x": 0.8159902691841125,
            "y": 0.6344678401947021,
            "z": -0.0020187986083328724
        },
        "RING_FINGER_PIP": {
            "x": 0.7873547077178955,
            "y": 0.6593009829521179,
            "z": -0.019178766757249832
        },
        "RING_FINGER_DIP": {
            "x": 0.7873189449310303,
            "y": 0.6966879367828369,
            "z": -0.016584977507591248
        },
        "RING_FINGER_TIP": {
            "x": 0.7888594269752502,
            "y": 0.7267847657203674,
            "z": -0.009127280674874783
        },
        "PINKY_MCP": {
            "x": 0.8440598249435425,
            "y": 0.6511659026145935,
            "z": -0.011156909167766571
        },
        "PINKY_PIP": {
            "x": 0.8161527514457703,
            "y": 0.6646233797073364,
            "z": -0.022150207310914993
        },
        "PINKY_DIP": {
            "x": 0.8135475516319275,
            "y": 0.6924679279327393,
            "z": -0.016827065497636795
        },
        "PINKY_TIP": {
            "x": 0.8167359232902527,
            "y": 0.7143879532814026,
            "z": -0.007648577447980642
        }
    }
}