{
    "gesture_class": "B-sign",
    "landmarks": {
        "WRIST": {
            "x": 0.6124807000160217,
            "y": 0.3877120614051819,
            "z": 3.6814645909544197e-07
        },
        "THUMB_CMC": {
            "x": 0.5842862129211426,
            "y": 0.3869665861129761,
            "z": -0.011773393489420414
        },
        "THUMB_MCP": {
            "x": 0.5584838390350342,
            "y": 0.3639678359031677,
            "z": -0.01988271251320839
        },
        "THUMB_IP": {
            "x": 0.5591707825660706,
            "y": 0.3347923755645752,
            "z": -0.02796812728047371
        },
        "THUMB_TIP": {
            "x": 0.5750278234481812,
            "y": 0.3179788291454315,
            "z": -0.036877281963825226
        },
        "INDEX_FINGER_MCP": {
            "x": 0.5401410460472107,
            "y": 0.3186587691307068,
            "z": -0.013822703622281551
        },
        "INDEX_FINGER_PIP": {
            "x": 0.5215415954589844,
            "y": 0.27930811047554016,
            "z": -0.02752443216741085
        },
        "INDEX_FINGER_DIP": {
            "x": 0.5099939107894897,
            "y": 0.2513456344604492,
            "z": -0.03963702172040939
        },
        "INDEX_FINGER_TIP": {
            "x": 0.5017107725143433,
            "y": 0.2278425097465515,
            "z": -0.048277970403432846
        },
        "MIDDLE_FINGER_MCP": {
            "x": 0.554754376411438,
            "y": 0.3096520006656647,
            "z": -0.018299836665391922
        },
        "MIDDLE_FINGER_PIP": {
            "x": 0.5337182879447937,
            "y": 0.26671624183654785,
            "z": -0.029656121507287025
        },
        "MIDDLE_FINGER_DIP": {
            "x": 0.5203291773796082,
            "y": 0.23578988015651703,
            "z": -0.04039397090673447
        },
        "MIDDLE_FINGER_TIP": {
            "x": 0.5105764269828796,
            "y": 0.21001747250556946,
            "z": -0.047825515270233154
        },
        "RING_FINGER_MCP": {
            "x": 0.5722030401229858,
            "y": 0.30668437480926514,
            "z": -0.024316152557730675
        },
        "RING_FINGER_PIP": {
            "x": 0.5521622896194458,
            "y": 0.26726555824279785,
            "z": -0.03356553986668587
        },
        "RING_FINGER_DIP": {
            "x": 0.5392957329750061,
            "y": 0.24035042524337769,
            "z": -0.04117262363433838
        },
        "RING_FINGER_TIP": {
            "x": 0.530384361743927,
            "y": 0.21828442811965942,
            "z": -0.04643886908888817
        },
        "PINKY_MCP": {
            "x": 0.5927551984786987,
            "y": 0.3089302182197571,
            "z": -0.0319761298596859
        },
        "PINKY_PIP": {
            "x": 0.5772655010223389,
            "y": 0.2800576984882355,
            "z": -0.03935849294066429
        },
        "PINKY_DIP": {
            "x": 0.5660308599472046,
            "y": 0.2608836591243744,
            "z": -0.042506784200668335
        },
        "PINKY_TIP": {
            "x": 0.5569249391555786,
            "y": 0.24513527750968933,
            "z": -0.044644251465797424
        }
    }
}